{"assets":{"66560BE5CFF8F01FEBC16FCF9AFCC775":{"type":"texture","index":3,"assetRequest":{"type":"slide","state":"incoming","slide":"AAC03A9A-2EE1-4006-A2EB-85AE8B1A1DCD"},"url":{"web":"assets/66560BE5CFF8F01FEBC16FCF9AFCC775.svg"},"width":1024,"height":768},"7C597F3FB1ABE40CF176BEF664029FB7":{"type":"texture","index":2,"assetRequest":{"type":"slide","state":"outgoing","slide":"D9433726-5947-428F-A554-7984E936C271"},"url":{"web":"assets/7C597F3FB1ABE40CF176BEF664029FB7.svg"},"width":1024,"height":768}},"events":[{"effects":[{"beginTime":0,"baseLayer":{"animations":[],"initialState":{"affineTransform":[1,0,0,1,0,0],"masksToBounds":false,"rotation":0,"scale":1,"position":{"pointX":512,"pointY":384},"width":1024,"sublayerTransform":[1,0,0,0,0,1,0,0,0,0,1,0,0,0,0,1],"contentsRect":{"y":0,"x":0,"width":1,"height":1},"opacity":1,"edgeAntialiasingMask":251658240,"height":768,"hidden":false,"anchorPoint":{"pointX":0.5,"pointY":0.5}},"objectID":"0","layers":[{"animations":[],"initialState":{"affineTransform":[1,0,0,1,0,0],"masksToBounds":false,"rotation":0,"scale":1,"position":{"pointX":512,"pointY":384},"width":1024,"sublayerTransform":[1,0,0,0,0,1,0,0,0,0,1,-0.0004922987690640373,0,0,0,1],"contentsRect":{"y":0,"x":0,"width":1,"height":1},"opacity":1,"edgeAntialiasingMask":251658240,"height":768,"hidden":false,"anchorPoint":{"pointX":0.5,"pointY":0.5}},"layers":[{"animations":[],"layers":[],"initialState":{"affineTransform":[1,0,0,1,0,0],"masksToBounds":false,"rotation":0,"scale":1,"position":{"pointX":512,"pointY":384},"width":1024,"sublayerTransform":[1,0,0,0,0,1,0,0,0,0,1,0,0,0,0,1],"contentsRect":{"y":0,"x":0,"width":1,"height":1},"opacity":1,"edgeAntialiasingMask":0,"height":768,"hidden":false,"anchorPoint":{"pointX":0.5,"pointY":0.5}},"texture":"66560BE5CFF8F01FEBC16FCF9AFCC775"},{"animations":[{"timeOffset":0,"from":{"scalar":false},"beginTime":0,"repeatCount":0,"fillMode":"both","property":"hidden","autoreverses":false,"duration":0.01,"to":{"scalar":true}}],"layers":[],"initialState":{"affineTransform":[1,0,0,1,0,0],"masksToBounds":false,"rotation":0,"scale":1,"position":{"pointX":512,"pointY":384},"width":1024,"sublayerTransform":[1,0,0,0,0,1,0,0,0,0,1,0,0,0,0,1],"contentsRect":{"y":0,"x":0,"width":1,"height":1},"opacity":1,"edgeAntialiasingMask":0,"height":768,"hidden":false,"anchorPoint":{"pointX":0.5,"pointY":0.5}},"texture":"7C597F3FB1ABE40CF176BEF664029FB7"}]}]},"effects":[],"duration":0.01,"type":"transition","name":"none","objectID":"0"}],"automaticPlay":false,"hyperlinks":[{"url":"http://www.packtpub.com","targetRectangle":{"y":611.9999949932098,"x":155.162798671167,"width":369.5256000000001,"height":74.912386083603}}],"accessibility":[{"text":"Books","targetRectangle":{"y":62,"x":414.816,"width":194.3679999999999,"height":76.1435546875}},{"text":"Mastering Object-Oriented Python","targetRectangle":{"y":195,"x":92.79999867116703,"width":485.2547999999999,"height":37.11238708496094}},{"text":"Python Essentials","targetRectangle":{"y":233,"x":92.79999867116703,"width":251.7156,"height":74.91238608360288}},{"text":"Functional Python Programming","targetRectangle":{"y":308.799998998642,"x":92.79999867116703,"width":455.7564,"height":74.91238608360288}},{"text":"Python for Secret Agents","targetRectangle":{"y":384.5999979972839,"x":92.79999867116703,"width":354.3173999999999,"height":74.91238608360294}},{"text":"Python for Secret Agents II","targetRectangle":{"y":460.3999969959259,"x":92.79999867116703,"width":379.8377999999999,"height":74.912386083603}},{"text":"The Python Cookbook","targetRectangle":{"y":536.1999959945679,"x":92.79999867116703,"width":315.7308,"height":74.912386083603}},{"text":"See http://www.packtpub.com","targetRectangle":{"y":611.9999949932098,"x":92.79999867116703,"width":431.8884,"height":74.912386083603}}],"baseLayer":{"animations":[],"initialState":{"affineTransform":[1,0,0,1,0,0],"masksToBounds":false,"rotation":0,"scale":1,"position":{"pointX":512,"pointY":384},"width":1024,"sublayerTransform":[1,0,0,0,0,1,0,0,0,0,1,0,0,0,0,1],"contentsRect":{"y":0,"x":0,"width":1,"height":1},"opacity":1,"edgeAntialiasingMask":251658240,"height":768,"hidden":false,"anchorPoint":{"pointX":0.5,"pointY":0.5}},"objectID":"0","layers":[{"animations":[],"initialState":{"affineTransform":[1,0,0,1,0,0],"masksToBounds":false,"rotation":0,"scale":1,"position":{"pointX":512,"pointY":384},"width":1024,"sublayerTransform":[1,0,0,0,0,1,0,0,0,0,1,-0.0004922987690640373,0,0,0,1],"contentsRect":{"y":0,"x":0,"width":1,"height":1},"opacity":1,"edgeAntialiasingMask":251658240,"height":768,"hidden":false,"anchorPoint":{"pointX":0.5,"pointY":0.5}},"layers":[{"animations":[],"layers":[],"initialState":{"affineTransform":[1,0,0,1,0,0],"masksToBounds":false,"rotation":0,"scale":1,"position":{"pointX":512,"pointY":384},"width":1024,"sublayerTransform":[1,0,0,0,0,1,0,0,0,0,1,0,0,0,0,1],"contentsRect":{"y":0,"x":0,"width":1,"height":1},"opacity":1,"edgeAntialiasingMask":0,"height":768,"hidden":false,"anchorPoint":{"pointX":0.5,"pointY":0.5}},"texture":"7C597F3FB1ABE40CF176BEF664029FB7"}]}]}}]}